st_webcam/__init__.py
st_webcam/st_webcam.py
st_webcam-0.1.1.dist-info/LICENSE
st_webcam-0.1.1.dist-info/METADATA
st_webcam-0.1.1.dist-info/WHEEL
st_webcam-0.1.1.dist-info/top_level.txt
st_webcam-0.1.1.dist-info/RECORD
