Metadata-Version: 2.1
Name: st_webcam
Version: 0.1.1
Summary: Effortless webcam integration for computer vision projects with Streamlit.
Home-page: https://github.com/SaarthRajan/st_webcam
Author: SaarthRajan
Author-email: saarth.rajan@uwaterloo.ca
License: MIT
Keywords: Computer Vision,Streamlit,Python,Webcam,Artificial Intelligence
Classifier: Programming Language :: Python :: 3.8
Classifier: Programming Language :: Python :: 3.9
Classifier: Programming Language :: Python :: 3.10
Classifier: License :: OSI Approved :: MIT License
Classifier: Development Status :: 5 - Production/Stable
Classifier: Operating System :: OS Independent
Classifier: Intended Audience :: Developers
Classifier: Intended Audience :: Science/Research
Classifier: Natural Language :: English
Classifier: Programming Language :: Python :: 3
Classifier: Topic :: Software Development :: Libraries :: Python Modules
Classifier: Topic :: Multimedia :: Video
License-File: LICENSE
Requires-Dist: opencv-python<5.0.0,>=4.0.0
Requires-Dist: streamlit<2.0.0,>=1.0.0
